nhanes/__init__.py
nhanes/get_NHANES_from_R.py
nhanes/load.py
nhanes/utils.py
nhanes/combined_data/2017-2018/NHANES_data_2017-2018.tsv
nhanes/combined_data/2017-2018/NHANES_metadata_2017-2018.tsv
nhanes/combined_data/2017-2018/NHANES_variable_coding_2017-2018.pkl
nhanes/config/datasets.json
nhanes/config/vars_to_keep.json
nhanes-0.5.1.data/scripts/make_combined_NHANES_data.py
nhanes-0.5.1.dist-info/LICENSE
nhanes-0.5.1.dist-info/METADATA
nhanes-0.5.1.dist-info/WHEEL
nhanes-0.5.1.dist-info/top_level.txt
nhanes-0.5.1.dist-info/RECORD
